kerberos_proxy_auth/bootstrap.py
kerberos_proxy_auth/wrapt_pip.py
kerberos_proxy_auth/wrapt_requests.py
kerberos_proxy_auth/wrapt_urllib3.py
kerberos_proxy_auth-0.0.2.data/data/lib/site-packages/kerberos-proxy-auth-init.pth
kerberos_proxy_auth-0.0.2.dist-info/LICENSE
kerberos_proxy_auth-0.0.2.dist-info/METADATA
kerberos_proxy_auth-0.0.2.dist-info/WHEEL
kerberos_proxy_auth-0.0.2.dist-info/top_level.txt
kerberos_proxy_auth-0.0.2.dist-info/RECORD
