Metadata-Version: 2.1
Name: kerberos-proxy-auth
Version: 0.0.2
Summary: This package patches requests at runtime to authenticate with kerberos proxy (negotiate)
Home-page: https://github.com/Rdataflow/kerberos-proxy-auth
Author: Rdataflow
Author-email: waldgis@bafu.admin.ch
License: BSD
License-File: LICENSE
Requires-Dist: wrapt (>=1.10.4)
Requires-Dist: requests-kerberos (>=0.14.0)
